filedgr_lib_ipfs/__init__.py
filedgr_lib_ipfs/ipfs_client.py
filedgr_lib_ipfs/my_io/__init__.py
filedgr_lib_ipfs/my_io/my_file_io.py
filedgr_ipfs_libs-0.0.28.dist-info/METADATA
filedgr_ipfs_libs-0.0.28.dist-info/WHEEL
filedgr_ipfs_libs-0.0.28.dist-info/top_level.txt
filedgr_ipfs_libs-0.0.28.dist-info/RECORD
